tno/mpc/encryption_schemes/dgk/__init__.py
tno/mpc/encryption_schemes/dgk/dgk.py
tno/mpc/encryption_schemes/dgk/py.typed
tno/mpc/encryption_schemes/dgk/test/__init__.py
tno/mpc/encryption_schemes/dgk/test/test_encryption.py
tno/mpc/encryption_schemes/dgk/test/test_equality.py
tno/mpc/encryption_schemes/dgk/test/test_keygen.py
tno/mpc/encryption_schemes/dgk/test/test_serialization.py
tno.mpc.encryption_schemes.dgk-3.0.5.dist-info/LICENSE
tno.mpc.encryption_schemes.dgk-3.0.5.dist-info/METADATA
tno.mpc.encryption_schemes.dgk-3.0.5.dist-info/WHEEL
tno.mpc.encryption_schemes.dgk-3.0.5.dist-info/top_level.txt
tno.mpc.encryption_schemes.dgk-3.0.5.dist-info/RECORD
