Metadata-Version: 2.1
Name: tno.mpc.encryption_schemes.dgk
Version: 3.0.5
Summary: Implementation of the Damgard, Geisler and Kroigard (DGK) cryptosystem
Author-email: TNO PET Lab <petlab@tno.nl>
Maintainer-email: TNO PET Lab <petlab@tno.nl>
License: Apache License, Version 2.0
Project-URL: Homepage, https://pet.tno.nl/
Project-URL: Documentation, https://docs.pet.tno.nl/mpc/encryption_schemes/dgk/3.0.5
Project-URL: Source, https://github.com/TNO-Mpc/encryption_schemes.dgk
Keywords: TNO,MPC,multi-party computation,encryption schemes,dgk,Damgard, Geisler and Kroigard,cryptosystem
Platform: any
Classifier: License :: OSI Approved :: Apache Software License
Classifier: Programming Language :: Python :: 3
Classifier: Operating System :: OS Independent
Classifier: Intended Audience :: Developers
Classifier: Intended Audience :: Information Technology
Classifier: Intended Audience :: Science/Research
Classifier: Typing :: Typed
Classifier: Topic :: Security :: Cryptography
Requires-Python: >=3.8
License-File: LICENSE
Requires-Dist: tno.mpc.encryption_schemes.templates~=4.1
Requires-Dist: tno.mpc.encryption_schemes.utils~=0.9
Provides-Extra: gmpy
Requires-Dist: tno.mpc.encryption_schemes.utils[gmpy]; extra == "gmpy"
Provides-Extra: communication
Requires-Dist: tno.mpc.communication~=4.8; extra == "communication"
Provides-Extra: tests
Requires-Dist: tno.mpc.encryption_schemes.dgk[communication]; extra == "tests"
Requires-Dist: pytest>=8.1; extra == "tests"
Requires-Dist: pytest-asyncio; extra == "tests"
Requires-Dist: sympy~=1.3; extra == "tests"
